{
  "id": "giro",
  "name": "Giromon",
  "frame1_url": "https://humulos.com/digimon/images/dot/vbbe/giro.gif",
  "frame2_url": "https://humulos.com/digimon/images/dot/vbbe/frame2/giro.gif",
  "artwork_url": "https://humulos.com/digimon/images/art/giro.jpg",
  "appearances": [
    {
      "dim_id": "pulse",
      "dim_name": "Pulsemon",
      "stage": "V"
    }
  ],
  "evolution_conditions": [
    {
      "from_digimon": [
        "reppa",
        "bladekuwaga"
      ],
      "requirements": {
        "PP": "10+",
        "Vital Values": "2,000+",
        "Battles": "10+",
        "Win Ratio": "40%+"
      }
    },
    {
      "from_digimon": [
        "thunderball"
      ],
      "requirements": {
        "PP": "8+",
        "Vital Values": "2,000+",
        "Battles": "10+",
        "Win Ratio": "40%+"
      }
    }
  ],
  "details": {
    "name_jp": "Giromon",
    "name_en": "Giromon",
    "attribute": "Vaccine",
    "stage_text": "Stage V (Perfect)",
    "activity": "Indoor",
    "stats": {
      "bp": "5000",
      "hp": "4400",
      "ap": "1450"
    },
    "schedule": {
      "activity_type": "Indoor",
      "critical_hit": "Turn 4"
    },
    "evolves_from": [
      {
        "id": "reppa",
        "name": "Reppamon",
        "conditions": "10+ PP, 2,000+ Vital Values, 10+ Battles, 40%+ Win Ratio"
      },
      {
        "id": "thunderball",
        "name": "Thunderballmon",
        "conditions": "8+ PP, 2,000+ Vital Values, 10+ Battles, 40%+ Win Ratio"
      },
      {
        "id": "bladekuwaga",
        "name": "Blade Kuwagamon",
        "conditions": "10+ PP, 2,000+ Vital Values, 10+ Battles, 40%+ Win Ratio"
      }
    ],
    "evolves_to": [
      {
        "id": "raijin",
        "name": "Raijinmon",
        "conditions": "25+ PP, 2,500+ Vital Values, 15+ Battles, 60%+ Win Ratio"
      },
      {
        "id": "raiden",
        "name": "Raidenmon",
        "conditions": "15+ PP, 1,500+ Vital Values, 15+ Battles, 40%+ Win Ratio"
      }
    ]
  }
}