{
  "id": "bluco",
  "name": "Blucomon",
  "frame1_url": "https://humulos.com/digimon/images/dot/vbdm/bluco.gif",
  "frame2_url": "https://humulos.com/digimon/images/dot/vbdm/frame2/bluco.gif",
  "artwork_url": "https://humulos.com/digimon/images/art/bluco.jpg",
  "appearances": [
    {
      "dim_id": "bfa",
      "dim_name": "Blizzard Fang",
      "stage": "III"
    }
  ],
  "evolution_conditions": [],
  "details": {
    "name_jp": "Blucomon",
    "name_en": "Blucomon",
    "attribute": "Data",
    "stage_text": "Stage III (Child)",
    "activity": "Normal",
    "stats": {
      "dp": "10 (★1)",
      "hp": "3",
      "ap": "2"
    },
    "schedule": {
      "awake_hours": "09:00 - 21:00",
      "critical_hit": "Turn 3"
    },
    "evolves_from": [
      {
        "id": "hiyari",
        "name": "Hiyarimon",
        "conditions": "No requirements"
      }
    ],
    "evolves_to": [
      {
        "id": "yukidaru",
        "name": "Yukidarumon",
        "conditions": "10+ Trophies, 1,300+ Vital Values, 8+ Battles"
      },
      {
        "id": "paledra",
        "name": "Paledramon",
        "conditions": "8+ Trophies, 900+ Vital Values, 5+ Battles"
      },
      {
        "id": "hyouga",
        "name": "Hyougamon",
        "conditions": "5+ Trophies, 600+ Vital Values, 3+ Battles"
      },
      {
        "id": "moose",
        "name": "Moosemon",
        "conditions": "• 0-4 Trophies• 0-599 Vital Values• 0-2 Battles"
      }
    ]
  }
}